phenopipe/__init__.py
phenopipe/bucket/__init__.py
phenopipe/bucket/copy_from_bucket_func.py
phenopipe/bucket/copy_to_bucket_func.py
phenopipe/bucket/ls_bucket_func.py
phenopipe/bucket/read_csv_from_bucket_func.py
phenopipe/bucket/remove_from_bucket_func.py
phenopipe/bucket/write_csv_to_bucket_func.py
phenopipe/desc_funcs/__init__.py
phenopipe/desc_funcs/summarize_n.py
phenopipe/pipe.py
phenopipe/query_builders/__init__.py
phenopipe/query_builders/cpt_procedure_query_builder.py
phenopipe/query_builders/fixed_queries/__init__.py
phenopipe/query_builders/fixed_queries/approx_resting_hr_query.py
phenopipe/query_builders/fixed_queries/bmi_query.py
phenopipe/query_builders/fixed_queries/bout_cadence_query.py
phenopipe/query_builders/fixed_queries/bp_query.py
phenopipe/query_builders/fixed_queries/cadence_pattern_query.py
phenopipe/query_builders/fixed_queries/daily_hr_query.py
phenopipe/query_builders/fixed_queries/dbp_query.py
phenopipe/query_builders/fixed_queries/death_cause_query.py
phenopipe/query_builders/fixed_queries/death_query.py
phenopipe/query_builders/fixed_queries/demographics_query.py
phenopipe/query_builders/fixed_queries/deprivation_index_query.py
phenopipe/query_builders/fixed_queries/ef_query.py
phenopipe/query_builders/fixed_queries/fitbit_query.py
phenopipe/query_builders/fixed_queries/height_query.py
phenopipe/query_builders/fixed_queries/high_bp_query.py
phenopipe/query_builders/fixed_queries/hr_query.py
phenopipe/query_builders/fixed_queries/inpatient_visit_query.py
phenopipe/query_builders/fixed_queries/primary_consent_date_query.py
phenopipe/query_builders/fixed_queries/sbp_query.py
phenopipe/query_builders/fixed_queries/sdann_query.py
phenopipe/query_builders/fixed_queries/ses_query.py
phenopipe/query_builders/fixed_queries/sleep_query.py
phenopipe/query_builders/fixed_queries/state_of_residency_query.py
phenopipe/query_builders/fixed_queries/wear_study_query.py
phenopipe/query_builders/fixed_queries/wear_time_hr_query.py
phenopipe-0.5.0.dist-info/LICENSE
phenopipe-0.5.0.dist-info/METADATA
phenopipe-0.5.0.dist-info/WHEEL
phenopipe-0.5.0.dist-info/RECORD
