Metadata-Version: 2.3
Name: phenopipe
Version: 0.5.0
Summary: 
License: GNU GENERAL PUBLIC LICENSE
Author: cakarac
Author-email: cakar.adnancihan@gmail.com
Requires-Python: >=3.10
Classifier: License :: Other/Proprietary License
Classifier: Programming Language :: Python :: 3
Classifier: Programming Language :: Python :: 3.10
Classifier: Programming Language :: Python :: 3.11
Classifier: Programming Language :: Python :: 3.12
Classifier: Programming Language :: Python :: 3.13
Provides-Extra: databricks
Requires-Dist: databricks-connect (>=13.3,<13.4) ; extra == "databricks"
Requires-Dist: google-cloud-bigquery (>=3.34.0,<4.0.0)
Requires-Dist: inflection (>=0.5.1,<0.6.0)
Requires-Dist: polars (>=1.31.0,<2.0.0)
Requires-Dist: pydantic (>=2.11.7,<3.0.0)
Requires-Dist: pyyaml (>=6.0.2,<7.0.0)
Requires-Dist: spark ; extra == "databricks"
